Metadata-Version: 1.0
Name: gaus-bi-distrib
Version: 1.0
Summary: Gaussian and Binomial distributions
Home-page: UNKNOWN
Author: S. M. Asif Mahfuz
Author-email: asif.mahfuz001@gmail.com
License: UNKNOWN
Platform: UNKNOWN
